pyfunc_ensembler_runner/__init__.py
pyfunc_ensembler_runner/__main__.py
pyfunc_ensembler_runner/ensembler_runner.py
pyfunc_ensembler_runner/handler.py
pyfunc_ensembler_runner/server.py
tests/__init__.py
tests/conftest.py
tests/test_ensembler_runner.py
nops_pyfunc_ensembler_service-0.0.0.dist-info/METADATA
nops_pyfunc_ensembler_service-0.0.0.dist-info/WHEEL
nops_pyfunc_ensembler_service-0.0.0.dist-info/top_level.txt
nops_pyfunc_ensembler_service-0.0.0.dist-info/RECORD
